lcw_data_platform_scaffold/__init__.py
lcw_data_platform_scaffold/scaffold.py
lcw_data_platform_scaffold-0.1.1.dist-info/LICENSE
lcw_data_platform_scaffold-0.1.1.dist-info/METADATA
lcw_data_platform_scaffold-0.1.1.dist-info/WHEEL
lcw_data_platform_scaffold-0.1.1.dist-info/entry_points.txt
lcw_data_platform_scaffold-0.1.1.dist-info/RECORD
