Metadata-Version: 2.1
Name: lcw_data_platform_scaffold
Version: 0.1.1
Summary: Scaffold Azure data engineering artefacts for multiple LCW data products
Author: Amitesh Bhattacharya
Author-email: amiteshbhattacharya58@gmail.com
Requires-Python: >=3.8,<4.0
Classifier: Programming Language :: Python :: 3
Classifier: Programming Language :: Python :: 3.8
Classifier: Programming Language :: Python :: 3.9
Classifier: Programming Language :: Python :: 3.10
Classifier: Programming Language :: Python :: 3.11
Classifier: Programming Language :: Python :: 3.12
Requires-Dist: click (>=8.1,<9.0)
